LICENSE
README.md
setup.cfg
setup.py
./swisscore_scheduler/__init__.py
./swisscore_scheduler/creation_helper.py
./swisscore_scheduler/scheduler.py
./swisscore_scheduler/tasks.py
./swisscore_scheduler/utils.py
swisscore_scheduler.egg-info/PKG-INFO
swisscore_scheduler.egg-info/SOURCES.txt
swisscore_scheduler.egg-info/dependency_links.txt
swisscore_scheduler.egg-info/not-zip-safe
swisscore_scheduler.egg-info/top_level.txt