Metadata-Version: 2.1
Name: swisscore-scheduler
Version: 0.0.2
Summary: An easy to use scheduler that works with both regular and coroutine functions
Home-page: https://github.com/SwissCorePy/swisscore-scheduler
Author: SwissCorePy
Author-email: swisscore.py@gmail.com
License: gpl-3.0
Platform: UNKNOWN
Classifier: Programming Language :: Python :: 3
Classifier: Programming Language :: Python :: 3.10
Classifier: Development Status :: 4 - Beta
Classifier: Environment :: Console
Classifier: License :: OSI Approved :: GNU General Public License v3 (GPLv3)
Requires-Python: >=3.10
License-File: LICENSE
